MANIFEST.in
README.rst
requirements.txt
setup.py
django_os_geocoder.egg-info/PKG-INFO
django_os_geocoder.egg-info/SOURCES.txt
django_os_geocoder.egg-info/dependency_links.txt
django_os_geocoder.egg-info/requires.txt
django_os_geocoder.egg-info/top_level.txt
geocoder/__init__.py
geocoder/models.py
geocoder/urls.py
geocoder/views.py
geocoder/management/__init__.py
geocoder/management/commands/__init__.py
geocoder/management/commands/load_places_from_OS_50k_gazetteer.py
geocoder/management/commands/load_places_from_OS_locator.py
geocoder/migrations/0001_initial.py
geocoder/migrations/0002_auto__add_place.py
geocoder/migrations/0003_auto__add_index_place_name.py
geocoder/migrations/__init__.py
geocoder/tests/__init__.py
geocoder/tests/commands.py
geocoder/tests/models.py
geocoder/tests/views.py
geocoder/tests/test_data/50kgaz2013_sample.txt
geocoder/tests/test_data/OS_Locator2013_1_OPEN_sample.txt