Metadata-Version: 1.0
Name: django-os-geocoder
Version: 0.1.6
Summary: A Django app that lets you load Ordnance Survey data and use it to find places.
Home-page: https://github.com/mysociety/django-os-geocoder
Author: mySociety
Author-email: programmers@mysociety.org
License: UNKNOWN
Platform: UNKNOWN
Classifier: Framework :: Django
